[
  {
    "id": "energieerzeugung1",
    "measure": "percent",
    "progress": 32.86,
    "evaluation": "quantitative",
    "status": "in_progress"
  },
  {
    "id": "energieerzeugung2",
    "measure": "percent",
    "progress": 9,
    "evaluation": "quantitative",
    "status": "in_progress"
  },
  {
    "id": "energieerzeugung3",
    "measure": "binary",
    "evaluation": "qualitative",
    "status": "in_progress"
  },
  {
    "id": "energieerzeugung4",
    "measure": "percent",
    "progress": 0,
    "evaluation": "quantitative",
    "status": "unknown"
  },
  {
    "id": "energieerzeugung5",
    "measure": "binary",
    "evaluation": "quantitative",
    "status": "unknown"
  },
  {
    "id": "energieerzeugung6",
    "measure": "binary",
    "evaluation": "quantitative",
    "status": "unknown"
  },
  {
    "id": "energieerzeugung7",
    "measure": "binary",
    "evaluation": "quantitative",
    "status": "unknown"
  },
  {
    "id": "energieerzeugung8",
    "measure": "binary",
    "evaluation": "quantitative",
    "status": "unknown"
  },
  {
    "id": "energieerzeugung9",
    "measure": "binary",
    "evaluation": "qualitative",
    "status": "in_progress"
  },
  {
    "id": "energieerzeugung10",
    "measure": "binary",
    "evaluation": "quantitative",
    "status": "unknown"
  },
  {
    "id": "energieerzeugung11",
    "measure": "binary",
    "evaluation": "qualitative",
    "status": "in_progress"
  },
  {
    "id": "energieerzeugung12",
    "measure": "binary",
    "evaluation": "qualitative",
    "status": "in_progress"
  },
  {
    "id": "energieerzeugung13",
    "measure": "percent",
    "progress": 0,
    "evaluation": "quantitative",
    "status": "unknown"
  },
  {
    "id": "mobilitaet1",
    "measure": "percent",
    "progress": 0,
    "status": "in_progress"
  }
]
